omi/__init__.py
omi/bluetooth.py
omi/decoder.py
omi/discover_characteristics.py
omi/py.typed
omi/transcribe.py
omi_sdk-0.2.1.dist-info/METADATA
omi_sdk-0.2.1.dist-info/WHEEL
omi_sdk-0.2.1.dist-info/entry_points.txt
omi_sdk-0.2.1.dist-info/top_level.txt
omi_sdk-0.2.1.dist-info/RECORD
