Metadata-Version: 2.4
Name: omi-sdk
Version: 0.2.1
Summary: Python SDK for Omi wearable device
Author-email: Omi Community <support@omi.me>, Tae <0xkevtae@gmail.com>
License: MIT
Project-URL: Homepage, https://www.omi.me/
Project-URL: Repository, https://github.com/BasedHardware/omi
Project-URL: Documentation, https://docs.omi.me/doc/developer/sdk/python
Keywords: omi,bluetooth,audio,transcription,deepgram,wearable
Classifier: Development Status :: 4 - Beta
Classifier: Intended Audience :: Developers
Classifier: License :: OSI Approved :: MIT License
Classifier: Operating System :: OS Independent
Classifier: Programming Language :: Python :: 3
Classifier: Programming Language :: Python :: 3.10
Classifier: Programming Language :: Python :: 3.11
Classifier: Programming Language :: Python :: 3.12
Classifier: Topic :: Multimedia :: Sound/Audio
Classifier: Topic :: Communications
Classifier: Topic :: System :: Hardware
Requires-Python: >=3.10
Requires-Dist: aenum==3.1.15
Requires-Dist: aiofiles==24.1.0
Requires-Dist: aiohappyeyeballs==2.6.1
Requires-Dist: aiohttp==3.11.14
Requires-Dist: aiosignal==1.3.2
Requires-Dist: anyio==4.9.0
Requires-Dist: async-timeout==4.0.3
Requires-Dist: attrs==25.3.0
Requires-Dist: bleak==0.22.3
Requires-Dist: certifi==2025.1.31
Requires-Dist: dataclasses-json==0.6.7
Requires-Dist: deepgram-sdk==2.12.0
Requires-Dist: deprecation==2.1.0
Requires-Dist: exceptiongroup==1.2.2
Requires-Dist: frozenlist==1.5.0
Requires-Dist: h11==0.14.0
Requires-Dist: httpcore==1.0.7
Requires-Dist: httpx==0.28.1
Requires-Dist: idna==3.10
Requires-Dist: marshmallow==3.26.1
Requires-Dist: multidict==6.2.0
Requires-Dist: mypy-extensions==1.0.0
Requires-Dist: opuslib==3.0.1
Requires-Dist: packaging==24.2
Requires-Dist: propcache==0.3.0
Requires-Dist: pyobjc-core==10.3.2; sys_platform == "darwin"
Requires-Dist: pyobjc-framework-Cocoa==10.3.2; sys_platform == "darwin"
Requires-Dist: pyobjc-framework-CoreBluetooth==10.3.2; sys_platform == "darwin"
Requires-Dist: pyobjc-framework-libdispatch==10.3.2; sys_platform == "darwin"
Requires-Dist: sniffio==1.3.1
Requires-Dist: typing-inspect==0.9.0
Requires-Dist: typing_extensions==4.12.2
Requires-Dist: websockets>=10.0
Requires-Dist: yarl==1.18.3
Provides-Extra: dev
Requires-Dist: pytest>=7.0; extra == "dev"
Requires-Dist: pytest-asyncio>=0.21.0; extra == "dev"
Requires-Dist: black>=23.0; extra == "dev"
Requires-Dist: isort>=5.12; extra == "dev"
Requires-Dist: mypy>=1.0; extra == "dev"
